weightipy/__init__.py
weightipy/rim.py
weightipy/version.py
weightipy/weight_engine.py
weightipy-0.4.0.dist-info/licenses/LICENSE.txt
weightipy-0.4.0.dist-info/METADATA
weightipy-0.4.0.dist-info/WHEEL
weightipy-0.4.0.dist-info/top_level.txt
weightipy-0.4.0.dist-info/RECORD
