Metadata-Version: 2.4
Name: weightipy
Version: 0.4.0
Author: Remi Sebastian Kits
Author-email: kaitumisuuringute.keskus@gmail.com
License-File: LICENSE.txt
Requires-Dist: numpy
Requires-Dist: scipy
Requires-Dist: pandas
Requires-Dist: decorator
Requires-Dist: watchdog
Requires-Dist: requests
Dynamic: author
Dynamic: author-email
Dynamic: description
Dynamic: description-content-type
Dynamic: license-file
Dynamic: requires-dist
